{
    "weekly_forecast": [
        {
            "date": "2026-07-23",
            "retrogrades": [
                {
                    "date": "2026-07-23",
                    "body": "Mercury"
                },
                {
                    "date": "2026-07-23",
                    "body": "Neptune"
                },
                {
                    "date": "2026-07-23",
                    "body": "Pluto"
                }
            ],
            "aspects": [
                {
                    "planet1": "mercury",
                    "planet2": "venus",
                    "aspect": "sextile",
                    "angle": 58.183661216696876,
                    "meaning": "Collaborating Energy"
                },
                {
                    "planet1": "mercury",
                    "planet2": "mars",
                    "aspect": "semi-sextile",
                    "angle": 29.420357063727977,
                    "meaning": "Potential Energy"
                },
                {
                    "planet1": "mercury",
                    "planet2": "saturn",
                    "aspect": "square",
                    "angle": 91.62272860194633,
                    "meaning": "Conflicting Energy"
                },
                {
                    "planet1": "mercury",
                    "planet2": "uranus",
                    "aspect": "semi-square",
                    "angle": 41.670848790557,
                    "meaning": "Dynamic Energy"
                },
                {
                    "planet1": "venus",
                    "planet2": "mercury",
                    "aspect": "sextile",
                    "angle": 58.183661216696876,
                    "meaning": "Collaborating Energy"
                },
                {
                    "planet1": "venus",
                    "planet2": "mars",
                    "aspect": "square",
                    "angle": 87.60401828042485,
                    "meaning": "Conflicting Energy"
                },
                {
                    "planet1": "venus",
                    "planet2": "jupiter",
                    "aspect": "semi-square",
                    "angle": 39.57513558664998,
                    "meaning": "Dynamic Energy"
                },
                {
                    "planet1": "venus",
                    "planet2": "saturn",
                    "aspect": "inconjunct",
                    "angle": 149.80638981864323,
                    "meaning": "Disrupting Energy"
                },
                {
                    "planet1": "mars",
                    "planet2": "mercury",
                    "aspect": "semi-sextile",
                    "angle": 29.420357063727977,
                    "meaning": "Potential Energy"
                },
                {
                    "planet1": "mars",
                    "planet2": "venus",
                    "aspect": "square",
                    "angle": 87.60401828042485,
                    "meaning": "Conflicting Energy"
                },
                {
                    "planet1": "mars",
                    "planet2": "jupiter",
                    "aspect": "semi-square",
                    "angle": 48.028882693774875,
                    "meaning": "Dynamic Energy"
                },
                {
                    "planet1": "mars",
                    "planet2": "saturn",
                    "aspect": "sextile",
                    "angle": 62.20237153821836,
                    "meaning": "Collaborating Energy"
                },
                {
                    "planet1": "mars",
                    "planet2": "neptune",
                    "aspect": "quintile",
                    "angle": 72.5864694993028,
                    "meaning": "Expressing Energy"
                },
                {
                    "planet1": "jupiter",
                    "planet2": "venus",
                    "aspect": "semi-square",
                    "angle": 39.57513558664998,
                    "meaning": "Dynamic Energy"
                },
                {
                    "planet1": "jupiter",
                    "planet2": "mars",
                    "aspect": "semi-square",
                    "angle": 48.028882693774875,
                    "meaning": "Dynamic Energy"
                },
                {
                    "planet1": "jupiter",
                    "planet2": "uranus",
                    "aspect": "sextile",
                    "angle": 60.2793744206039,
                    "meaning": "Collaborating Energy"
                },
                {
                    "planet1": "jupiter",
                    "planet2": "neptune",
                    "aspect": "trine",
                    "angle": 120.61535219307767,
                    "meaning": "Supporting Energy"
                },
                {
                    "planet1": "saturn",
                    "planet2": "mercury",
                    "aspect": "square",
                    "angle": 91.62272860194633,
                    "meaning": "Conflicting Energy"
                },
                {
                    "planet1": "saturn",
                    "planet2": "venus",
                    "aspect": "inconjunct",
                    "angle": 149.80638981864323,
                    "meaning": "Disrupting Energy"
                },
                {
                    "planet1": "saturn",
                    "planet2": "mars",
                    "aspect": "sextile",
                    "angle": 62.20237153821836,
                    "meaning": "Collaborating Energy"
                },
                {
                    "planet1": "saturn",
                    "planet2": "uranus",
                    "aspect": "semi-square",
                    "angle": 49.95187981138933,
                    "meaning": "Dynamic Energy"
                },
                {
                    "planet1": "uranus",
                    "planet2": "mercury",
                    "aspect": "semi-square",
                    "angle": 41.670848790557,
                    "meaning": "Dynamic Energy"
                },
                {
                    "planet1": "uranus",
                    "planet2": "jupiter",
                    "aspect": "sextile",
                    "angle": 60.2793744206039,
                    "meaning": "Collaborating Energy"
                },
                {
                    "planet1": "uranus",
                    "planet2": "saturn",
                    "aspect": "semi-square",
                    "angle": 49.95187981138933,
                    "meaning": "Dynamic Energy"
                },
                {
                    "planet1": "uranus",
                    "planet2": "neptune",
                    "aspect": "sextile",
                    "angle": 60.33597777247377,
                    "meaning": "Collaborating Energy"
                },
                {
                    "planet1": "neptune",
                    "planet2": "mars",
                    "aspect": "quintile",
                    "angle": 72.5864694993028,
                    "meaning": "Expressing Energy"
                },
                {
                    "planet1": "neptune",
                    "planet2": "jupiter",
                    "aspect": "trine",
                    "angle": 120.61535219307767,
                    "meaning": "Supporting Energy"
                },
                {
                    "planet1": "neptune",
                    "planet2": "uranus",
                    "aspect": "sextile",
                    "angle": 60.33597777247377,
                    "meaning": "Collaborating Energy"
                }
            ],
            "recommendations": {
                "do": [
                    "Collaborate with others and share ideas",
                    "Take advantage of harmonious energies",
                    "Recognize and integrate subtle energies",
                    "Adjust your plans to accommodate new insights",
                    "Address minor irritations before they escalate",
                    "Express your creativity and unique ideas",
                    "Work through challenges constructively"
                ],
                "dont": [
                    "Ignore small issues that could grow",
                    "Suppress your individuality",
                    "Ignore small conflicts",
                    "Overlook minor details",
                    "Avoid conflicts or procrastinate",
                    "Become complacent",
                    "Miss opportunities for cooperation"
                ]
            }
        },
        {
            "date": "2026-07-24",
            "retrogrades": [
                {
                    "date": "2026-07-24",
                    "body": "Neptune"
                },
                {
                    "date": "2026-07-24",
                    "body": "Pluto"
                }
            ],
            "aspects": [
                {
                    "planet1": "mercury",
                    "planet2": "venus",
                    "aspect": "sextile",
                    "angle": 59.29912602773271,
                    "meaning": "Collaborating Energy"
                },
                {
                    "planet1": "mercury",
                    "planet2": "mars",
                    "aspect": "semi-sextile",
                    "angle": 28.691890045076633,
                    "meaning": "Potential Energy"
                },
                {
                    "planet1": "mercury",
                    "planet2": "saturn",
                    "aspect": "square",
                    "angle": 91.57439285706724,
                    "meaning": "Conflicting Energy"
                },
                {
                    "planet1": "mercury",
                    "planet2": "uranus",
                    "aspect": "semi-square",
                    "angle": 41.590002700929006,
                    "meaning": "Dynamic Energy"
                },
                {
                    "planet1": "venus",
                    "planet2": "mercury",
                    "aspect": "sextile",
                    "angle": 59.29912602773271,
                    "meaning": "Collaborating Energy"
                },
                {
                    "planet1": "venus",
                    "planet2": "mars",
                    "aspect": "square",
                    "angle": 87.99101607280934,
                    "meaning": "Conflicting Energy"
                },
                {
                    "planet1": "venus",
                    "planet2": "jupiter",
                    "aspect": "semi-square",
                    "angle": 40.42665016242918,
                    "meaning": "Dynamic Energy"
                },
                {
                    "planet1": "venus",
                    "planet2": "saturn",
                    "aspect": "inconjunct",
                    "angle": 150.87351888479995,
                    "meaning": "Disrupting Energy"
                },
                {
                    "planet1": "mars",
                    "planet2": "mercury",
                    "aspect": "semi-sextile",
                    "angle": 28.691890045076633,
                    "meaning": "Potential Energy"
                },
                {
                    "planet1": "mars",
                    "planet2": "venus",
                    "aspect": "square",
                    "angle": 87.99101607280934,
                    "meaning": "Conflicting Energy"
                },
                {
                    "planet1": "mars",
                    "planet2": "jupiter",
                    "aspect": "semi-square",
                    "angle": 47.56436591038016,
                    "meaning": "Dynamic Energy"
                },
                {
                    "planet1": "mars",
                    "planet2": "saturn",
                    "aspect": "sextile",
                    "angle": 62.882502811990605,
                    "meaning": "Collaborating Energy"
                },
                {
                    "planet1": "mars",
                    "planet2": "neptune",
                    "aspect": "quintile",
                    "angle": 73.2807599201751,
                    "meaning": "Expressing Energy"
                },
                {
                    "planet1": "jupiter",
                    "planet2": "venus",
                    "aspect": "semi-square",
                    "angle": 40.42665016242918,
                    "meaning": "Dynamic Energy"
                },
                {
                    "planet1": "jupiter",
                    "planet2": "mars",
                    "aspect": "semi-square",
                    "angle": 47.56436591038016,
                    "meaning": "Dynamic Energy"
                },
                {
                    "planet1": "jupiter",
                    "planet2": "uranus",
                    "aspect": "sextile",
                    "angle": 60.462478566232534,
                    "meaning": "Collaborating Energy"
                },
                {
                    "planet1": "jupiter",
                    "planet2": "neptune",
                    "aspect": "trine",
                    "angle": 120.84512583055526,
                    "meaning": "Supporting Energy"
                },
                {
                    "planet1": "saturn",
                    "planet2": "mercury",
                    "aspect": "square",
                    "angle": 91.57439285706724,
                    "meaning": "Conflicting Energy"
                },
                {
                    "planet1": "saturn",
                    "planet2": "venus",
                    "aspect": "inconjunct",
                    "angle": 150.87351888479995,
                    "meaning": "Disrupting Energy"
                },
                {
                    "planet1": "saturn",
                    "planet2": "mars",
                    "aspect": "sextile",
                    "angle": 62.882502811990605,
                    "meaning": "Collaborating Energy"
                },
                {
                    "planet1": "saturn",
                    "planet2": "uranus",
                    "aspect": "semi-square",
                    "angle": 49.98439015613823,
                    "meaning": "Dynamic Energy"
                },
                {
                    "planet1": "uranus",
                    "planet2": "mercury",
                    "aspect": "semi-square",
                    "angle": 41.590002700929006,
                    "meaning": "Dynamic Energy"
                },
                {
                    "planet1": "uranus",
                    "planet2": "jupiter",
                    "aspect": "sextile",
                    "angle": 60.462478566232534,
                    "meaning": "Collaborating Energy"
                },
                {
                    "planet1": "uranus",
                    "planet2": "saturn",
                    "aspect": "semi-square",
                    "angle": 49.98439015613823,
                    "meaning": "Dynamic Energy"
                },
                {
                    "planet1": "uranus",
                    "planet2": "neptune",
                    "aspect": "sextile",
                    "angle": 60.38264726432272,
                    "meaning": "Collaborating Energy"
                },
                {
                    "planet1": "neptune",
                    "planet2": "mars",
                    "aspect": "quintile",
                    "angle": 73.2807599201751,
                    "meaning": "Expressing Energy"
                },
                {
                    "planet1": "neptune",
                    "planet2": "jupiter",
                    "aspect": "trine",
                    "angle": 120.84512583055526,
                    "meaning": "Supporting Energy"
                },
                {
                    "planet1": "neptune",
                    "planet2": "uranus",
                    "aspect": "sextile",
                    "angle": 60.38264726432272,
                    "meaning": "Collaborating Energy"
                }
            ],
            "recommendations": {
                "do": [
                    "Collaborate with others and share ideas",
                    "Take advantage of harmonious energies",
                    "Recognize and integrate subtle energies",
                    "Adjust your plans to accommodate new insights",
                    "Address minor irritations before they escalate",
                    "Express your creativity and unique ideas",
                    "Work through challenges constructively"
                ],
                "dont": [
                    "Ignore small issues that could grow",
                    "Suppress your individuality",
                    "Ignore small conflicts",
                    "Overlook minor details",
                    "Avoid conflicts or procrastinate",
                    "Become complacent",
                    "Miss opportunities for cooperation"
                ]
            }
        },
        {
            "date": "2026-07-25",
            "retrogrades": [
                {
                    "date": "2026-07-25",
                    "body": "Neptune"
                },
                {
                    "date": "2026-07-25",
                    "body": "Pluto"
                }
            ],
            "aspects": [
                {
                    "planet1": "mercury",
                    "planet2": "venus",
                    "aspect": "sextile",
                    "angle": 60.316302070923,
                    "meaning": "Collaborating Energy"
                },
                {
                    "planet1": "mercury",
                    "planet2": "mars",
                    "aspect": "semi-sextile",
                    "angle": 28.059209800599717,
                    "meaning": "Potential Energy"
                },
                {
                    "planet1": "mercury",
                    "planet2": "saturn",
                    "aspect": "square",
                    "angle": 91.62235625054576,
                    "meaning": "Conflicting Energy"
                },
                {
                    "planet1": "mercury",
                    "planet2": "uranus",
                    "aspect": "semi-square",
                    "angle": 41.60438088851946,
                    "meaning": "Dynamic Energy"
                },
                {
                    "planet1": "venus",
                    "planet2": "mercury",
                    "aspect": "sextile",
                    "angle": 60.316302070923,
                    "meaning": "Collaborating Energy"
                },
                {
                    "planet1": "venus",
                    "planet2": "mars",
                    "aspect": "square",
                    "angle": 88.37551187152272,
                    "meaning": "Conflicting Energy"
                },
                {
                    "planet1": "venus",
                    "planet2": "jupiter",
                    "aspect": "semi-square",
                    "angle": 41.27439065254838,
                    "meaning": "Dynamic Energy"
                },
                {
                    "planet1": "venus",
                    "planet2": "saturn",
                    "aspect": "inconjunct",
                    "angle": 151.93865832146878,
                    "meaning": "Disrupting Energy"
                },
                {
                    "planet1": "mars",
                    "planet2": "mercury",
                    "aspect": "semi-sextile",
                    "angle": 28.059209800599717,
                    "meaning": "Potential Energy"
                },
                {
                    "planet1": "mars",
                    "planet2": "venus",
                    "aspect": "square",
                    "angle": 88.37551187152272,
                    "meaning": "Conflicting Energy"
                },
                {
                    "planet1": "mars",
                    "planet2": "jupiter",
                    "aspect": "semi-square",
                    "angle": 47.10112121897434,
                    "meaning": "Dynamic Energy"
                },
                {
                    "planet1": "mars",
                    "planet2": "saturn",
                    "aspect": "sextile",
                    "angle": 63.563146449946046,
                    "meaning": "Collaborating Energy"
                },
                {
                    "planet1": "mars",
                    "planet2": "neptune",
                    "aspect": "quintile",
                    "angle": 73.9743634718869,
                    "meaning": "Expressing Energy"
                },
                {
                    "planet1": "jupiter",
                    "planet2": "venus",
                    "aspect": "semi-square",
                    "angle": 41.27439065254838,
                    "meaning": "Dynamic Energy"
                },
                {
                    "planet1": "jupiter",
                    "planet2": "mars",
                    "aspect": "semi-square",
                    "angle": 47.10112121897434,
                    "meaning": "Dynamic Energy"
                },
                {
                    "planet1": "jupiter",
                    "planet2": "uranus",
                    "aspect": "sextile",
                    "angle": 60.64629230689408,
                    "meaning": "Collaborating Energy"
                },
                {
                    "planet1": "jupiter",
                    "planet2": "neptune",
                    "aspect": "trine",
                    "angle": 121.07548469086124,
                    "meaning": "Supporting Energy"
                },
                {
                    "planet1": "saturn",
                    "planet2": "mercury",
                    "aspect": "square",
                    "angle": 91.62235625054576,
                    "meaning": "Conflicting Energy"
                },
                {
                    "planet1": "saturn",
                    "planet2": "venus",
                    "aspect": "inconjunct",
                    "angle": 151.93865832146878,
                    "meaning": "Disrupting Energy"
                },
                {
                    "planet1": "saturn",
                    "planet2": "mars",
                    "aspect": "sextile",
                    "angle": 63.563146449946046,
                    "meaning": "Collaborating Energy"
                },
                {
                    "planet1": "saturn",
                    "planet2": "uranus",
                    "aspect": "semi-square",
                    "angle": 50.017975362026306,
                    "meaning": "Dynamic Energy"
                },
                {
                    "planet1": "uranus",
                    "planet2": "mercury",
                    "aspect": "semi-square",
                    "angle": 41.60438088851946,
                    "meaning": "Dynamic Energy"
                },
                {
                    "planet1": "uranus",
                    "planet2": "jupiter",
                    "aspect": "sextile",
                    "angle": 60.64629230689408,
                    "meaning": "Collaborating Energy"
                },
                {
                    "planet1": "uranus",
                    "planet2": "saturn",
                    "aspect": "semi-square",
                    "angle": 50.017975362026306,
                    "meaning": "Dynamic Energy"
                },
                {
                    "planet1": "uranus",
                    "planet2": "neptune",
                    "aspect": "sextile",
                    "angle": 60.42919238396717,
                    "meaning": "Collaborating Energy"
                },
                {
                    "planet1": "neptune",
                    "planet2": "mars",
                    "aspect": "quintile",
                    "angle": 73.9743634718869,
                    "meaning": "Expressing Energy"
                },
                {
                    "planet1": "neptune",
                    "planet2": "jupiter",
                    "aspect": "trine",
                    "angle": 121.07548469086124,
                    "meaning": "Supporting Energy"
                },
                {
                    "planet1": "neptune",
                    "planet2": "uranus",
                    "aspect": "sextile",
                    "angle": 60.42919238396717,
                    "meaning": "Collaborating Energy"
                }
            ],
            "recommendations": {
                "do": [
                    "Collaborate with others and share ideas",
                    "Take advantage of harmonious energies",
                    "Recognize and integrate subtle energies",
                    "Adjust your plans to accommodate new insights",
                    "Address minor irritations before they escalate",
                    "Express your creativity and unique ideas",
                    "Work through challenges constructively"
                ],
                "dont": [
                    "Ignore small issues that could grow",
                    "Suppress your individuality",
                    "Ignore small conflicts",
                    "Overlook minor details",
                    "Avoid conflicts or procrastinate",
                    "Become complacent",
                    "Miss opportunities for cooperation"
                ]
            }
        },
        {
            "date": "2026-07-26",
            "retrogrades": [
                {
                    "date": "2026-07-26",
                    "body": "Neptune"
                },
                {
                    "date": "2026-07-26",
                    "body": "Pluto"
                }
            ],
            "aspects": [
                {
                    "planet1": "mercury",
                    "planet2": "venus",
                    "aspect": "sextile",
                    "angle": 61.23240396065701,
                    "meaning": "Collaborating Energy"
                },
                {
                    "planet1": "mercury",
                    "planet2": "mars",
                    "aspect": "semi-sextile",
                    "angle": 27.524997473996777,
                    "meaning": "Potential Energy"
                },
                {
                    "planet1": "mercury",
                    "planet2": "saturn",
                    "aspect": "square",
                    "angle": 91.7693012837354,
                    "meaning": "Conflicting Energy"
                },
                {
                    "planet1": "mercury",
                    "planet2": "uranus",
                    "aspect": "semi-square",
                    "angle": 41.71667365575543,
                    "meaning": "Dynamic Energy"
                },
                {
                    "planet1": "venus",
                    "planet2": "mercury",
                    "aspect": "sextile",
                    "angle": 61.23240396065701,
                    "meaning": "Collaborating Energy"
                },
                {
                    "planet1": "venus",
                    "planet2": "mars",
                    "aspect": "square",
                    "angle": 88.75740143465379,
                    "meaning": "Conflicting Energy"
                },
                {
                    "planet1": "venus",
                    "planet2": "jupiter",
                    "aspect": "semi-square",
                    "angle": 42.11827091355312,
                    "meaning": "Dynamic Energy"
                },
                {
                    "planet1": "venus",
                    "planet2": "saturn",
                    "aspect": "inconjunct",
                    "angle": 153.0017052443924,
                    "meaning": "Disrupting Energy"
                },
                {
                    "planet1": "mars",
                    "planet2": "mercury",
                    "aspect": "semi-sextile",
                    "angle": 27.524997473996777,
                    "meaning": "Potential Energy"
                },
                {
                    "planet1": "mars",
                    "planet2": "venus",
                    "aspect": "square",
                    "angle": 88.75740143465379,
                    "meaning": "Conflicting Energy"
                },
                {
                    "planet1": "mars",
                    "planet2": "jupiter",
                    "aspect": "semi-square",
                    "angle": 46.63913052110067,
                    "meaning": "Dynamic Energy"
                },
                {
                    "planet1": "mars",
                    "planet2": "saturn",
                    "aspect": "sextile",
                    "angle": 64.24430380973862,
                    "meaning": "Collaborating Energy"
                },
                {
                    "planet1": "mars",
                    "planet2": "saturn",
                    "aspect": "quintile",
                    "angle": 64.24430380973862,
                    "meaning": "Expressing Energy"
                },
                {
                    "planet1": "mars",
                    "planet2": "neptune",
                    "aspect": "quintile",
                    "angle": 74.66727825025856,
                    "meaning": "Expressing Energy"
                },
                {
                    "planet1": "jupiter",
                    "planet2": "venus",
                    "aspect": "semi-square",
                    "angle": 42.11827091355312,
                    "meaning": "Dynamic Energy"
                },
                {
                    "planet1": "jupiter",
                    "planet2": "mars",
                    "aspect": "semi-square",
                    "angle": 46.63913052110067,
                    "meaning": "Dynamic Energy"
                },
                {
                    "planet1": "jupiter",
                    "planet2": "uranus",
                    "aspect": "sextile",
                    "angle": 60.83080670285932,
                    "meaning": "Collaborating Energy"
                },
                {
                    "planet1": "jupiter",
                    "planet2": "neptune",
                    "aspect": "trine",
                    "angle": 121.30640877135923,
                    "meaning": "Supporting Energy"
                },
                {
                    "planet1": "saturn",
                    "planet2": "mercury",
                    "aspect": "square",
                    "angle": 91.7693012837354,
                    "meaning": "Conflicting Energy"
                },
                {
                    "planet1": "saturn",
                    "planet2": "venus",
                    "aspect": "inconjunct",
                    "angle": 153.0017052443924,
                    "meaning": "Disrupting Energy"
                },
                {
                    "planet1": "saturn",
                    "planet2": "mars",
                    "aspect": "sextile",
                    "angle": 64.24430380973862,
                    "meaning": "Collaborating Energy"
                },
                {
                    "planet1": "saturn",
                    "planet2": "mars",
                    "aspect": "quintile",
                    "angle": 64.24430380973862,
                    "meaning": "Expressing Energy"
                },
                {
                    "planet1": "saturn",
                    "planet2": "uranus",
                    "aspect": "semi-square",
                    "angle": 50.052627627979966,
                    "meaning": "Dynamic Energy"
                },
                {
                    "planet1": "uranus",
                    "planet2": "mercury",
                    "aspect": "semi-square",
                    "angle": 41.71667365575543,
                    "meaning": "Dynamic Energy"
                },
                {
                    "planet1": "uranus",
                    "planet2": "jupiter",
                    "aspect": "sextile",
                    "angle": 60.83080670285932,
                    "meaning": "Collaborating Energy"
                },
                {
                    "planet1": "uranus",
                    "planet2": "saturn",
                    "aspect": "semi-square",
                    "angle": 50.052627627979966,
                    "meaning": "Dynamic Energy"
                },
                {
                    "planet1": "uranus",
                    "planet2": "neptune",
                    "aspect": "sextile",
                    "angle": 60.47560206849991,
                    "meaning": "Collaborating Energy"
                },
                {
                    "planet1": "neptune",
                    "planet2": "mars",
                    "aspect": "quintile",
                    "angle": 74.66727825025856,
                    "meaning": "Expressing Energy"
                },
                {
                    "planet1": "neptune",
                    "planet2": "jupiter",
                    "aspect": "trine",
                    "angle": 121.30640877135923,
                    "meaning": "Supporting Energy"
                },
                {
                    "planet1": "neptune",
                    "planet2": "uranus",
                    "aspect": "sextile",
                    "angle": 60.47560206849991,
                    "meaning": "Collaborating Energy"
                }
            ],
            "recommendations": {
                "do": [
                    "Collaborate with others and share ideas",
                    "Take advantage of harmonious energies",
                    "Recognize and integrate subtle energies",
                    "Adjust your plans to accommodate new insights",
                    "Address minor irritations before they escalate",
                    "Express your creativity and unique ideas",
                    "Work through challenges constructively"
                ],
                "dont": [
                    "Ignore small issues that could grow",
                    "Suppress your individuality",
                    "Ignore small conflicts",
                    "Overlook minor details",
                    "Avoid conflicts or procrastinate",
                    "Become complacent",
                    "Miss opportunities for cooperation"
                ]
            }
        },
        {
            "date": "2026-07-27",
            "retrogrades": [
                {
                    "date": "2026-07-27",
                    "body": "Neptune"
                },
                {
                    "date": "2026-07-27",
                    "body": "Pluto"
                }
            ],
            "aspects": [
                {
                    "planet1": "mercury",
                    "planet2": "venus",
                    "aspect": "sextile",
                    "angle": 62.045408430805054,
                    "meaning": "Collaborating Energy"
                },
                {
                    "planet1": "mercury",
                    "planet2": "mars",
                    "aspect": "semi-sextile",
                    "angle": 27.09117063379702,
                    "meaning": "Potential Energy"
                },
                {
                    "planet1": "mercury",
                    "planet2": "saturn",
                    "aspect": "square",
                    "angle": 92.01714669513144,
                    "meaning": "Conflicting Energy"
                },
                {
                    "planet1": "mercury",
                    "planet2": "uranus",
                    "aspect": "semi-square",
                    "angle": 41.928807722082794,
                    "meaning": "Dynamic Energy"
                },
                {
                    "planet1": "venus",
                    "planet2": "mercury",
                    "aspect": "sextile",
                    "angle": 62.045408430805054,
                    "meaning": "Collaborating Energy"
                },
                {
                    "planet1": "venus",
                    "planet2": "mars",
                    "aspect": "square",
                    "angle": 89.13657906460207,
                    "meaning": "Conflicting Energy"
                },
                {
                    "planet1": "venus",
                    "planet2": "jupiter",
                    "aspect": "semi-square",
                    "angle": 42.95820145326023,
                    "meaning": "Dynamic Energy"
                },
                {
                    "planet1": "venus",
                    "planet2": "saturn",
                    "aspect": "inconjunct",
                    "angle": 154.0625551259365,
                    "meaning": "Disrupting Energy"
                },
                {
                    "planet1": "mars",
                    "planet2": "mercury",
                    "aspect": "semi-sextile",
                    "angle": 27.09117063379702,
                    "meaning": "Potential Energy"
                },
                {
                    "planet1": "mars",
                    "planet2": "venus",
                    "aspect": "square",
                    "angle": 89.13657906460207,
                    "meaning": "Conflicting Energy"
                },
                {
                    "planet1": "mars",
                    "planet2": "jupiter",
                    "aspect": "semi-square",
                    "angle": 46.178377611341844,
                    "meaning": "Dynamic Energy"
                },
                {
                    "planet1": "mars",
                    "planet2": "saturn",
                    "aspect": "sextile",
                    "angle": 64.92597606133442,
                    "meaning": "Collaborating Energy"
                },
                {
                    "planet1": "mars",
                    "planet2": "saturn",
                    "aspect": "quintile",
                    "angle": 64.92597606133442,
                    "meaning": "Expressing Energy"
                },
                {
                    "planet1": "mars",
                    "planet2": "neptune",
                    "aspect": "quintile",
                    "angle": 75.35950236452793,
                    "meaning": "Expressing Energy"
                },
                {
                    "planet1": "jupiter",
                    "planet2": "venus",
                    "aspect": "semi-square",
                    "angle": 42.95820145326023,
                    "meaning": "Dynamic Energy"
                },
                {
                    "planet1": "jupiter",
                    "planet2": "mars",
                    "aspect": "semi-square",
                    "angle": 46.178377611341844,
                    "meaning": "Dynamic Energy"
                },
                {
                    "planet1": "jupiter",
                    "planet2": "uranus",
                    "aspect": "sextile",
                    "angle": 61.01601469962762,
                    "meaning": "Collaborating Energy"
                },
                {
                    "planet1": "jupiter",
                    "planet2": "neptune",
                    "aspect": "trine",
                    "angle": 121.53787997586977,
                    "meaning": "Supporting Energy"
                },
                {
                    "planet1": "saturn",
                    "planet2": "mercury",
                    "aspect": "square",
                    "angle": 92.01714669513144,
                    "meaning": "Conflicting Energy"
                },
                {
                    "planet1": "saturn",
                    "planet2": "venus",
                    "aspect": "inconjunct",
                    "angle": 154.0625551259365,
                    "meaning": "Disrupting Energy"
                },
                {
                    "planet1": "saturn",
                    "planet2": "mars",
                    "aspect": "sextile",
                    "angle": 64.92597606133442,
                    "meaning": "Collaborating Energy"
                },
                {
                    "planet1": "saturn",
                    "planet2": "mars",
                    "aspect": "quintile",
                    "angle": 64.92597606133442,
                    "meaning": "Expressing Energy"
                },
                {
                    "planet1": "saturn",
                    "planet2": "uranus",
                    "aspect": "semi-square",
                    "angle": 50.08833897304865,
                    "meaning": "Dynamic Energy"
                },
                {
                    "planet1": "uranus",
                    "planet2": "mercury",
                    "aspect": "semi-square",
                    "angle": 41.928807722082794,
                    "meaning": "Dynamic Energy"
                },
                {
                    "planet1": "uranus",
                    "planet2": "jupiter",
                    "aspect": "sextile",
                    "angle": 61.01601469962762,
                    "meaning": "Collaborating Energy"
                },
                {
                    "planet1": "uranus",
                    "planet2": "saturn",
                    "aspect": "semi-square",
                    "angle": 50.08833897304865,
                    "meaning": "Dynamic Energy"
                },
                {
                    "planet1": "uranus",
                    "planet2": "neptune",
                    "aspect": "sextile",
                    "angle": 60.52186527624215,
                    "meaning": "Collaborating Energy"
                },
                {
                    "planet1": "neptune",
                    "planet2": "mars",
                    "aspect": "quintile",
                    "angle": 75.35950236452793,
                    "meaning": "Expressing Energy"
                },
                {
                    "planet1": "neptune",
                    "planet2": "jupiter",
                    "aspect": "trine",
                    "angle": 121.53787997586977,
                    "meaning": "Supporting Energy"
                },
                {
                    "planet1": "neptune",
                    "planet2": "uranus",
                    "aspect": "sextile",
                    "angle": 60.52186527624215,
                    "meaning": "Collaborating Energy"
                }
            ],
            "recommendations": {
                "do": [
                    "Collaborate with others and share ideas",
                    "Take advantage of harmonious energies",
                    "Recognize and integrate subtle energies",
                    "Adjust your plans to accommodate new insights",
                    "Address minor irritations before they escalate",
                    "Express your creativity and unique ideas",
                    "Work through challenges constructively"
                ],
                "dont": [
                    "Ignore small issues that could grow",
                    "Suppress your individuality",
                    "Ignore small conflicts",
                    "Overlook minor details",
                    "Avoid conflicts or procrastinate",
                    "Become complacent",
                    "Miss opportunities for cooperation"
                ]
            }
        },
        {
            "date": "2026-07-28",
            "retrogrades": [
                {
                    "date": "2026-07-28",
                    "body": "Saturn"
                },
                {
                    "date": "2026-07-28",
                    "body": "Neptune"
                },
                {
                    "date": "2026-07-28",
                    "body": "Pluto"
                }
            ],
            "aspects": [
                {
                    "planet1": "mercury",
                    "planet2": "venus",
                    "aspect": "sextile",
                    "angle": 62.753967177100165,
                    "meaning": "Collaborating Energy"
                },
                {
                    "planet1": "mercury",
                    "planet2": "mars",
                    "aspect": "semi-sextile",
                    "angle": 26.758970554670185,
                    "meaning": "Potential Energy"
                },
                {
                    "planet1": "mercury",
                    "planet2": "saturn",
                    "aspect": "square",
                    "angle": 92.3671346371141,
                    "meaning": "Conflicting Energy"
                },
                {
                    "planet1": "mercury",
                    "planet2": "uranus",
                    "aspect": "semi-square",
                    "angle": 42.24203340161132,
                    "meaning": "Dynamic Energy"
                },
                {
                    "planet1": "venus",
                    "planet2": "mercury",
                    "aspect": "sextile",
                    "angle": 62.753967177100165,
                    "meaning": "Collaborating Energy"
                },
                {
                    "planet1": "venus",
                    "planet2": "mars",
                    "aspect": "square",
                    "angle": 89.51293773177035,
                    "meaning": "Conflicting Energy"
                },
                {
                    "planet1": "venus",
                    "planet2": "jupiter",
                    "aspect": "semi-square",
                    "angle": 43.794086906243734,
                    "meaning": "Dynamic Energy"
                },
                {
                    "planet1": "venus",
                    "planet2": "saturn",
                    "aspect": "inconjunct",
                    "angle": 155.12110181421428,
                    "meaning": "Disrupting Energy"
                },
                {
                    "planet1": "mars",
                    "planet2": "mercury",
                    "aspect": "semi-sextile",
                    "angle": 26.758970554670185,
                    "meaning": "Potential Energy"
                },
                {
                    "planet1": "mars",
                    "planet2": "venus",
                    "aspect": "square",
                    "angle": 89.51293773177035,
                    "meaning": "Conflicting Energy"
                },
                {
                    "planet1": "mars",
                    "planet2": "jupiter",
                    "aspect": "semi-square",
                    "angle": 45.718850825526616,
                    "meaning": "Dynamic Energy"
                },
                {
                    "planet1": "mars",
                    "planet2": "saturn",
                    "aspect": "sextile",
                    "angle": 65.60816408244392,
                    "meaning": "Collaborating Energy"
                },
                {
                    "planet1": "mars",
                    "planet2": "saturn",
                    "aspect": "quintile",
                    "angle": 65.60816408244392,
                    "meaning": "Expressing Energy"
                },
                {
                    "planet1": "mars",
                    "planet2": "neptune",
                    "aspect": "quintile",
                    "angle": 76.05103382217936,
                    "meaning": "Expressing Energy"
                },
                {
                    "planet1": "jupiter",
                    "planet2": "venus",
                    "aspect": "semi-square",
                    "angle": 43.794086906243734,
                    "meaning": "Dynamic Energy"
                },
                {
                    "planet1": "jupiter",
                    "planet2": "mars",
                    "aspect": "semi-square",
                    "angle": 45.718850825526616,
                    "meaning": "Dynamic Energy"
                },
                {
                    "planet1": "jupiter",
                    "planet2": "uranus",
                    "aspect": "sextile",
                    "angle": 61.201913672467754,
                    "meaning": "Collaborating Energy"
                },
                {
                    "planet1": "jupiter",
                    "planet2": "neptune",
                    "aspect": "trine",
                    "angle": 121.76988464770598,
                    "meaning": "Supporting Energy"
                },
                {
                    "planet1": "saturn",
                    "planet2": "mercury",
                    "aspect": "square",
                    "angle": 92.3671346371141,
                    "meaning": "Conflicting Energy"
                },
                {
                    "planet1": "saturn",
                    "planet2": "venus",
                    "aspect": "inconjunct",
                    "angle": 155.12110181421428,
                    "meaning": "Disrupting Energy"
                },
                {
                    "planet1": "saturn",
                    "planet2": "mars",
                    "aspect": "sextile",
                    "angle": 65.60816408244392,
                    "meaning": "Collaborating Energy"
                },
                {
                    "planet1": "saturn",
                    "planet2": "mars",
                    "aspect": "quintile",
                    "angle": 65.60816408244392,
                    "meaning": "Expressing Energy"
                },
                {
                    "planet1": "saturn",
                    "planet2": "uranus",
                    "aspect": "semi-square",
                    "angle": 50.12510123550279,
                    "meaning": "Dynamic Energy"
                },
                {
                    "planet1": "uranus",
                    "planet2": "mercury",
                    "aspect": "semi-square",
                    "angle": 42.24203340161132,
                    "meaning": "Dynamic Energy"
                },
                {
                    "planet1": "uranus",
                    "planet2": "jupiter",
                    "aspect": "sextile",
                    "angle": 61.201913672467754,
                    "meaning": "Collaborating Energy"
                },
                {
                    "planet1": "uranus",
                    "planet2": "saturn",
                    "aspect": "semi-square",
                    "angle": 50.12510123550279,
                    "meaning": "Dynamic Energy"
                },
                {
                    "planet1": "uranus",
                    "planet2": "neptune",
                    "aspect": "sextile",
                    "angle": 60.56797097523823,
                    "meaning": "Collaborating Energy"
                },
                {
                    "planet1": "neptune",
                    "planet2": "mars",
                    "aspect": "quintile",
                    "angle": 76.05103382217936,
                    "meaning": "Expressing Energy"
                },
                {
                    "planet1": "neptune",
                    "planet2": "jupiter",
                    "aspect": "trine",
                    "angle": 121.76988464770598,
                    "meaning": "Supporting Energy"
                },
                {
                    "planet1": "neptune",
                    "planet2": "uranus",
                    "aspect": "sextile",
                    "angle": 60.56797097523823,
                    "meaning": "Collaborating Energy"
                }
            ],
            "recommendations": {
                "do": [
                    "Collaborate with others and share ideas",
                    "Take advantage of harmonious energies",
                    "Recognize and integrate subtle energies",
                    "Adjust your plans to accommodate new insights",
                    "Address minor irritations before they escalate",
                    "Express your creativity and unique ideas",
                    "Work through challenges constructively"
                ],
                "dont": [
                    "Ignore small issues that could grow",
                    "Suppress your individuality",
                    "Ignore small conflicts",
                    "Overlook minor details",
                    "Avoid conflicts or procrastinate",
                    "Become complacent",
                    "Miss opportunities for cooperation"
                ]
            }
        },
        {
            "date": "2026-07-29",
            "retrogrades": [
                {
                    "date": "2026-07-29",
                    "body": "Saturn"
                },
                {
                    "date": "2026-07-29",
                    "body": "Neptune"
                },
                {
                    "date": "2026-07-29",
                    "body": "Pluto"
                }
            ],
            "aspects": [
                {
                    "planet1": "mercury",
                    "planet2": "venus",
                    "aspect": "sextile",
                    "angle": 63.3573230758344,
                    "meaning": "Collaborating Energy"
                },
                {
                    "planet1": "mercury",
                    "planet2": "mars",
                    "aspect": "semi-sextile",
                    "angle": 26.52904620883595,
                    "meaning": "Potential Energy"
                },
                {
                    "planet1": "mercury",
                    "planet2": "saturn",
                    "aspect": "square",
                    "angle": 92.81991452996664,
                    "meaning": "Conflicting Energy"
                },
                {
                    "planet1": "mercury",
                    "planet2": "uranus",
                    "aspect": "semi-square",
                    "angle": 42.65700845704768,
                    "meaning": "Dynamic Energy"
                },
                {
                    "planet1": "venus",
                    "planet2": "mercury",
                    "aspect": "sextile",
                    "angle": 63.3573230758344,
                    "meaning": "Collaborating Energy"
                },
                {
                    "planet1": "venus",
                    "planet2": "mars",
                    "aspect": "square",
                    "angle": 89.88636928467035,
                    "meaning": "Conflicting Energy"
                },
                {
                    "planet1": "venus",
                    "planet2": "jupiter",
                    "aspect": "semi-square",
                    "angle": 44.62584890881817,
                    "meaning": "Dynamic Energy"
                },
                {
                    "planet1": "venus",
                    "planet2": "saturn",
                    "aspect": "inconjunct",
                    "angle": 156.17723760580103,
                    "meaning": "Disrupting Energy"
                },
                {
                    "planet1": "mars",
                    "planet2": "mercury",
                    "aspect": "semi-sextile",
                    "angle": 26.52904620883595,
                    "meaning": "Potential Energy"
                },
                {
                    "planet1": "mars",
                    "planet2": "venus",
                    "aspect": "square",
                    "angle": 89.88636928467035,
                    "meaning": "Conflicting Energy"
                },
                {
                    "planet1": "mars",
                    "planet2": "jupiter",
                    "aspect": "semi-square",
                    "angle": 45.26052037585218,
                    "meaning": "Dynamic Energy"
                },
                {
                    "planet1": "mars",
                    "planet2": "saturn",
                    "aspect": "sextile",
                    "angle": 66.29086832113069,
                    "meaning": "Collaborating Energy"
                },
                {
                    "planet1": "mars",
                    "planet2": "saturn",
                    "aspect": "quintile",
                    "angle": 66.29086832113069,
                    "meaning": "Expressing Energy"
                },
                {
                    "planet1": "mars",
                    "planet2": "neptune",
                    "aspect": "quintile",
                    "angle": 76.74187037734143,
                    "meaning": "Expressing Energy"
                },
                {
                    "planet1": "jupiter",
                    "planet2": "venus",
                    "aspect": "semi-square",
                    "angle": 44.62584890881817,
                    "meaning": "Dynamic Energy"
                },
                {
                    "planet1": "jupiter",
                    "planet2": "mars",
                    "aspect": "semi-square",
                    "angle": 45.26052037585218,
                    "meaning": "Dynamic Energy"
                },
                {
                    "planet1": "jupiter",
                    "planet2": "uranus",
                    "aspect": "sextile",
                    "angle": 61.38848262406391,
                    "meaning": "Collaborating Energy"
                },
                {
                    "planet1": "jupiter",
                    "planet2": "neptune",
                    "aspect": "trine",
                    "angle": 122.00239075319361,
                    "meaning": "Supporting Energy"
                },
                {
                    "planet1": "saturn",
                    "planet2": "mercury",
                    "aspect": "square",
                    "angle": 92.81991452996664,
                    "meaning": "Conflicting Energy"
                },
                {
                    "planet1": "saturn",
                    "planet2": "venus",
                    "aspect": "inconjunct",
                    "angle": 156.17723760580103,
                    "meaning": "Disrupting Energy"
                },
                {
                    "planet1": "saturn",
                    "planet2": "mars",
                    "aspect": "sextile",
                    "angle": 66.29086832113069,
                    "meaning": "Collaborating Energy"
                },
                {
                    "planet1": "saturn",
                    "planet2": "mars",
                    "aspect": "quintile",
                    "angle": 66.29086832113069,
                    "meaning": "Expressing Energy"
                },
                {
                    "planet1": "saturn",
                    "planet2": "uranus",
                    "aspect": "semi-square",
                    "angle": 50.16290607291895,
                    "meaning": "Dynamic Energy"
                },
                {
                    "planet1": "uranus",
                    "planet2": "mercury",
                    "aspect": "semi-square",
                    "angle": 42.65700845704768,
                    "meaning": "Dynamic Energy"
                },
                {
                    "planet1": "uranus",
                    "planet2": "jupiter",
                    "aspect": "sextile",
                    "angle": 61.38848262406391,
                    "meaning": "Collaborating Energy"
                },
                {
                    "planet1": "uranus",
                    "planet2": "saturn",
                    "aspect": "semi-square",
                    "angle": 50.16290607291895,
                    "meaning": "Dynamic Energy"
                },
                {
                    "planet1": "uranus",
                    "planet2": "neptune",
                    "aspect": "sextile",
                    "angle": 60.6139081291297,
                    "meaning": "Collaborating Energy"
                },
                {
                    "planet1": "neptune",
                    "planet2": "mars",
                    "aspect": "quintile",
                    "angle": 76.74187037734143,
                    "meaning": "Expressing Energy"
                },
                {
                    "planet1": "neptune",
                    "planet2": "jupiter",
                    "aspect": "trine",
                    "angle": 122.00239075319361,
                    "meaning": "Supporting Energy"
                },
                {
                    "planet1": "neptune",
                    "planet2": "uranus",
                    "aspect": "sextile",
                    "angle": 60.6139081291297,
                    "meaning": "Collaborating Energy"
                }
            ],
            "recommendations": {
                "do": [
                    "Collaborate with others and share ideas",
                    "Take advantage of harmonious energies",
                    "Recognize and integrate subtle energies",
                    "Adjust your plans to accommodate new insights",
                    "Address minor irritations before they escalate",
                    "Express your creativity and unique ideas",
                    "Work through challenges constructively"
                ],
                "dont": [
                    "Ignore small issues that could grow",
                    "Suppress your individuality",
                    "Ignore small conflicts",
                    "Overlook minor details",
                    "Avoid conflicts or procrastinate",
                    "Become complacent",
                    "Miss opportunities for cooperation"
                ]
            }
        }
    ],
    "notifications": [
        {
            "upcoming_retrograde_alert": "Mercury retrograde on 2026-07-23, Neptune retrograde on 2026-07-23, Pluto retrograde on 2026-07-23, Neptune retrograde on 2026-07-24, Pluto retrograde on 2026-07-24, Neptune retrograde on 2026-07-25, Pluto retrograde on 2026-07-25, Neptune retrograde on 2026-07-26, Pluto retrograde on 2026-07-26, Neptune retrograde on 2026-07-27, Pluto retrograde on 2026-07-27, Saturn retrograde on 2026-07-28, Neptune retrograde on 2026-07-28, Pluto retrograde on 2026-07-28, Saturn retrograde on 2026-07-29, Neptune retrograde on 2026-07-29, Pluto retrograde on 2026-07-29",
            "daily_tip": "Reflect on the influences of the retrogrades."
        }
    ],
    "educational_content": [
        {
            "title": "Understanding Retrogrades",
            "content": "Retrogrades are periods when a planet appears to move backward in its orbit, as viewed from Earth. This is an optical illusion caused by differences in orbit speeds. During retrograde periods, the planet's energies are turned inward, making it a time for reflection and reassessment."
        },
        {
            "title": "How to Navigate Retrogrades",
            "content": "During retrogrades, it's best to avoid starting new projects or making major decisions. Instead, focus on introspection, reviewing past actions, and making adjustments. Be patient and allow more time for everything, as delays and misunderstandings are common."
        }
    ]
}